alipay/__init__.py
python_alipay-2021.4.29.dist-info/METADATA
python_alipay-2021.4.29.dist-info/WHEEL
python_alipay-2021.4.29.dist-info/top_level.txt
python_alipay-2021.4.29.dist-info/RECORD
